{
  "userExperience": {
    "aboutURL": "",
    "body": "",
    "companyLogoPath": "",
    "disableWelcomeScreen": true,
    "header": "",
    "welcomeBody": "",
    "welcomeButton": "",
    "welcomeHeader": "",
    "welcomeScreenItem1Description": "",
    "welcomeScreenItem1ImageName": "",
    "welcomeScreenItem1Title":"",
    "welcomeScreenItem2Description": "",
    "welcomeScreenItem2ImageName": "",
    "welcomeScreenItem2Title":"",
    "welcomeScreenItem3Description": "",
    "welcomeScreenItem3ImageName": "",
    "welcomeScreenItem3Title":""
  },
  "deviceStages": [
    {
      "id": 1,
      "title": "Xcode Command Line Tools",
      "iconPath": "file:///System/Applications/Utilities/Terminal.app/Contents/Resources/Terminal.icns",
      "installedPath": "/Applications/Xcode.app"
    },
    {
      "id": 2,
      "title": "Visual Studio Code",
      "iconPath": "file:///Applications/Visual%20Studio%20Code.app/Contents/Resources/Code.icns",
      "installedPath": "file:///Applications/Visual%20Studio%20Code.app"
    },
    {
      "id": 3,
      "title": "Slack",
      "iconPath": "file:///Applications/Slack.app/Contents/Resources/electron.icns",
      "installedPath": "file:///Applications/Slack.app"
    },
    {
      "id": 4,
      "title": "GitHub Desktop",
      "iconPath": "file:///Applications/GitHub%20Desktop.app/Contents/Resources/electron.icns",
      "installedPath": "file:///Applications/GitHub%20Desktop.app"
    }
  ]
}
